alibabacloud_aiccs20191015/__init__.py
alibabacloud_aiccs20191015/client.py
alibabacloud_aiccs20191015/models/__init__.py
alibabacloud_aiccs20191015/models/_add_hotline_number_request.py
alibabacloud_aiccs20191015/models/_add_hotline_number_response.py
alibabacloud_aiccs20191015/models/_add_hotline_number_response_body.py
alibabacloud_aiccs20191015/models/_add_hotline_number_shrink_request.py
alibabacloud_aiccs20191015/models/_add_outer_account_request.py
alibabacloud_aiccs20191015/models/_add_outer_account_response.py
alibabacloud_aiccs20191015/models/_add_outer_account_response_body.py
alibabacloud_aiccs20191015/models/_add_skill_group_request.py
alibabacloud_aiccs20191015/models/_add_skill_group_response.py
alibabacloud_aiccs20191015/models/_add_skill_group_response_body.py
alibabacloud_aiccs20191015/models/_aiccs_smart_call_operate_request.py
alibabacloud_aiccs20191015/models/_aiccs_smart_call_operate_response.py
alibabacloud_aiccs20191015/models/_aiccs_smart_call_operate_response_body.py
alibabacloud_aiccs20191015/models/_aiccs_smart_call_request.py
alibabacloud_aiccs20191015/models/_aiccs_smart_call_response.py
alibabacloud_aiccs20191015/models/_aiccs_smart_call_response_body.py
alibabacloud_aiccs20191015/models/_answer_call_request.py
alibabacloud_aiccs20191015/models/_answer_call_response.py
alibabacloud_aiccs20191015/models/_answer_call_response_body.py
alibabacloud_aiccs20191015/models/_attach_task_request.py
alibabacloud_aiccs20191015/models/_attach_task_response.py
alibabacloud_aiccs20191015/models/_attach_task_response_body.py
alibabacloud_aiccs20191015/models/_batch_create_quality_projects_request.py
alibabacloud_aiccs20191015/models/_batch_create_quality_projects_response.py
alibabacloud_aiccs20191015/models/_batch_create_quality_projects_response_body.py
alibabacloud_aiccs20191015/models/_cancel_ai_call_details_request.py
alibabacloud_aiccs20191015/models/_cancel_ai_call_details_response.py
alibabacloud_aiccs20191015-3.5.0.dist-info/LICENSE
alibabacloud_aiccs20191015-3.5.0.dist-info/METADATA
alibabacloud_aiccs20191015-3.5.0.dist-info/WHEEL
alibabacloud_aiccs20191015-3.5.0.dist-info/top_level.txt
alibabacloud_aiccs20191015-3.5.0.dist-info/RECORD
